webtraversallibrary/__init__.py
webtraversallibrary/actions.py
webtraversallibrary/classifiers.py
webtraversallibrary/color.py
webtraversallibrary/config.py
webtraversallibrary/error.py
webtraversallibrary/geometry.py
webtraversallibrary/goals.py
webtraversallibrary/graphics.py
webtraversallibrary/helpers.py
webtraversallibrary/javascript.py
webtraversallibrary/logging_utils.py
webtraversallibrary/policies.py
webtraversallibrary/processtools.py
webtraversallibrary/scraper.py
webtraversallibrary/screenshot.py
webtraversallibrary/selector.py
webtraversallibrary/snapshot.py
webtraversallibrary/version.py
webtraversallibrary/version_check.py
webtraversallibrary/view.py
webtraversallibrary/webdrivers.py
webtraversallibrary/window.py
webtraversallibrary/workflow.py
webtraversallibrary/configs/default.json
webtraversallibrary/configs/desktop.json
webtraversallibrary/configs/firefox_desktop.json
webtraversallibrary/configs/firefox_mobile.json
webtraversallibrary/configs/headless.json
webtraversallibrary/configs/mhtml.json
webtraversallibrary/configs/quick.json
webtraversallibrary/configs/save.json
webtraversallibrary/driver_check/__init__.py
webtraversallibrary/driver_check/os_functions.py
webtraversallibrary/extension/__init__.py
webtraversallibrary/extension/wtl_extension.crx
webtraversallibrary/font/LICENSE.txt
webtraversallibrary/font/OpenSans-Regular.ttf
webtraversallibrary/font/__init__.py
webtraversallibrary/js/annotate.js
webtraversallibrary/js/clear_highlights.js
webtraversallibrary/js/click_element.js
webtraversallibrary/js/delete_element.js
webtraversallibrary/js/disable_animations.js
webtraversallibrary/js/dom.js
webtraversallibrary/js/element_exists.js
webtraversallibrary/js/fill_text.js
webtraversallibrary/js/find_active_elements.js
webtraversallibrary/js/find_iframe_name.js
webtraversallibrary/js/find_viewport.js
webtraversallibrary/js/get_element_metadata.js
webtraversallibrary/js/get_full_page_height.js
webtraversallibrary-0.13.2.dist-info/LICENSE
webtraversallibrary-0.13.2.dist-info/METADATA
webtraversallibrary-0.13.2.dist-info/NOTICE
webtraversallibrary-0.13.2.dist-info/WHEEL
webtraversallibrary-0.13.2.dist-info/top_level.txt
webtraversallibrary-0.13.2.dist-info/RECORD
