Metadata-Version: 2.1
Name: webtraversallibrary
Version: 0.13.2
Summary: Abstractions of web interactions
Home-page: https://github.com/klarna-incubator/webtraversallibrary
Author: Klarna Bank AB
Author-email: marcus.naslund@klarna.com
License: UNKNOWN
Platform: UNKNOWN
Classifier: Programming Language :: Python :: 3.7
Classifier: Programming Language :: Python :: 3.8
Classifier: Programming Language :: Python :: 3.9
Classifier: License :: OSI Approved :: Apache Software License
Classifier: Operating System :: OS Independent
Requires-Python: >=3.7
Requires-Dist: beautifulsoup4 (>=4.8)
Requires-Dist: html5lib (>=1.0.1)
Requires-Dist: pillow (>=7.1)
Requires-Dist: requests (>=2.24)
Requires-Dist: selenium (>=3.141)
Requires-Dist: soupsieve (>=2.0tld)
Requires-Dist: urllib3
Requires-Dist: prodict (>=0.8)
